movoid_fsm/__init__.py
movoid_fsm/fsm.py
movoid_fsm-1.0.0.dist-info/METADATA
movoid_fsm-1.0.0.dist-info/WHEEL
movoid_fsm-1.0.0.dist-info/top_level.txt
movoid_fsm-1.0.0.dist-info/RECORD
