Metadata-Version: 2.2
Name: movoid_fsm
Version: 1.0.0
Home-page: 
Author: movoid
Author-email: bobrobotsun@163.com
Requires-Dist: movoid_function
Dynamic: author
Dynamic: author-email
Dynamic: description
Dynamic: description-content-type
Dynamic: requires-dist
